phonenumber_confirmation/__init__.py
phonenumber_confirmation/admin.py
phonenumber_confirmation/app_settings.py
phonenumber_confirmation/apps.py
phonenumber_confirmation/fields.py
phonenumber_confirmation/managers.py
phonenumber_confirmation/models.py
phonenumber_confirmation/serializers.py
phonenumber_confirmation/tests.py
phonenumber_confirmation/urls.py
phonenumber_confirmation/views.py
phonenumber_confirmation/migrations/0001_initial.py
phonenumber_confirmation/migrations/0002_auto_20200403_1444.py
phonenumber_confirmation/migrations/__init__.py
tests/__init__.py
tests/test.py
tests/test_settings.py
django_Rest_phonenumber_confirmation-0.2.dist-info/LICENSE
django_Rest_phonenumber_confirmation-0.2.dist-info/METADATA
django_Rest_phonenumber_confirmation-0.2.dist-info/WHEEL
django_Rest_phonenumber_confirmation-0.2.dist-info/top_level.txt
django_Rest_phonenumber_confirmation-0.2.dist-info/RECORD
