Metadata-Version: 2.1
Name: django-Rest-phonenumber-confirmation
Version: 0.2
Summary: Phone number confirmation
Home-page: https://github.com/thomas545/django-Rest-phonenumber-confirmation
Author: Thomas Adel
Author-email: thomas.adel31@gmail.com
License: MIT
Keywords: django-phonenumber-confirmation phonenumber confirmations twilio django-twilio
Platform: UNKNOWN
Classifier: Framework :: Django
Classifier: Intended Audience :: Developers
Classifier: Intended Audience :: System Administrators
Classifier: Operating System :: OS Independent
Classifier: Topic :: Software Development
Requires-Dist: Django (>=3.0)
Requires-Dist: djangorestframework (>=3.11.0)
Requires-Dist: django-phonenumber-field (>=4.0.0)
Requires-Dist: phonenumbers (>=8.12.1)
Requires-Dist: twilio (>=6.0.0)
